{
  "id": "shell_min",
  "name": "Shell (Lite)",
  "description": "Lite Basalt shell with core navigation and run commands",
  "platforms": [
    "esp32",
    "stm32",
    "rp2040",
    "avr",
    "pic",
    "pic16"
  ],
  "provides": [
    "shell"
  ],
  "depends": [
    "uart"
  ],
  "conflicts": [
    "shell_full",
    "shell_tiny"
  ],
  "defines": [
    "BASALT_ENABLE_SHELL_MIN"
  ],
  "default_enabled": false,
  "notes": [
    "Requires UART for input",
    "Balanced shell for constrained builds"
  ]
}
